Metadata-Version: 2.1
Name: rmrentryutils
Version: 0.1.0
Summary: rmrentryutils
Author: jesus212406
Author-email: jesus212406@0xckh4.gpa.lu
